scriptdb/__init__.py
scriptdb/__init__.pyi
scriptdb/_cache_index.py
scriptdb/_rowfactory.py
scriptdb/abstractdb.py
scriptdb/asynccachedb.py
scriptdb/asyncdb.py
scriptdb/conversion.py
scriptdb/daemonizable_aiosqlite.py
scriptdb/dbbuilder.py
scriptdb/py.typed
scriptdb/sqlite_backend.py
scriptdb/synccachedb.py
scriptdb/syncdb.py
scriptdb-1.1.2.dist-info/LICENSE
scriptdb-1.1.2.dist-info/METADATA
scriptdb-1.1.2.dist-info/WHEEL
scriptdb-1.1.2.dist-info/top_level.txt
scriptdb-1.1.2.dist-info/RECORD
