Metadata-Version: 2.1
Name: scriptdb
Version: 1.1.2
Summary: Simple SQLite sync/async wrapper with migration support for use in ad-hoc scripts
Author: ScriptDB Contributors
License: MIT License
Project-URL: Homepage, https://github.com/MihanEntalpo/ScriptDB
Project-URL: Repository, https://github.com/MihanEntalpo/ScriptDB
Keywords: sqlite,migrations,asyncio,database
Classifier: Development Status :: 4 - Beta
Classifier: Intended Audience :: Developers
Classifier: License :: OSI Approved :: MIT License
Classifier: Programming Language :: Python
Classifier: Topic :: Database
Classifier: Topic :: Database :: Front-Ends
Classifier: Topic :: Software Development :: Libraries
Classifier: Topic :: Software Development :: Libraries :: Python Modules
Requires-Python: >=3.8
License-File: LICENSE
Provides-Extra: async
Requires-Dist: aiosqlite>=0.19; extra == "async"
Provides-Extra: pysqlite
Requires-Dist: pysqlite3-binary>=0.5.0; extra == "pysqlite"
Provides-Extra: test
Requires-Dist: pytest>=7.0; extra == "test"
Requires-Dist: pytest-asyncio>=0.20; extra == "test"
Requires-Dist: aiosqlite>=0.19; extra == "test"
Requires-Dist: pytest-cov>=4.1; extra == "test"
Requires-Dist: ruff>=0.0.275; extra == "test"
Requires-Dist: mypy<1.11,>=1.0; extra == "test"
